{
  "autorun": false,
  "terminals": [
    {
      "name": "Client:dev",
      "focus": true,
      "command": "pnpm run dev:client"
    },
    {
      "name": "Server:dev",
      "focus": true,
      "command": "pnpm run dev:server"
    },
    {
      "name": "Bot:dev",
      "focus": true,
      "command": "pnpm run dev:bot"
    },
    {
      "name": "Add Shaadcn component",
      "focus": true,
      "cwd": "[workspaceFolder]/packages/client",
      "command": "npx shadcn@latest add ",
      "execute": false
    }
  ]
}
